drkv_ec2_utils_v2/__init__.py
drkv_ec2_utils_v2/ec2_utils.py
drkv_ec2_utils_v2-2.14.4.dist-info/METADATA
drkv_ec2_utils_v2-2.14.4.dist-info/WHEEL
drkv_ec2_utils_v2-2.14.4.dist-info/top_level.txt
drkv_ec2_utils_v2-2.14.4.dist-info/RECORD
