Metadata-Version: 2.2
Name: drkv_ec2_utils_v2
Version: 2.14.4
Summary: Python module to onboard the EC2 Utils Library V2
Home-page: https://github.com/drkv-com/ec2-utils-v2
Download-URL: https://github.com/drkv-com/ec2-utils-v2/archive/refs/tags/v0.1.0.tar.gz
Author: drkv - Duesseldorf - Germany
Author-email: m.kirchhof@drkv.com
Classifier: Development Status :: 4 - Beta
Classifier: Intended Audience :: Developers
Classifier: License :: OSI Approved :: MIT License
Classifier: Programming Language :: Python :: 3
Classifier: Programming Language :: Python :: 3.6
Classifier: Programming Language :: Python :: 3.7
Classifier: Programming Language :: Python :: 3.8
Classifier: Programming Language :: Python :: 3.9
Classifier: Programming Language :: Python :: 3.10
Classifier: Programming Language :: Python :: 3.11
Requires-Dist: boto3>=1.28.10
Requires-Dist: pycryptodome>=3.20.0
Dynamic: author
Dynamic: author-email
Dynamic: classifier
Dynamic: download-url
Dynamic: home-page
Dynamic: requires-dist
Dynamic: summary
